multienc/__init__.py
multienc/crypto.py
multienc/enums.py
multienc/errors.py
multienc/helpers.py
multienc/test_crypto.py
multienc-0.1.0.dist-info/METADATA
multienc-0.1.0.dist-info/WHEEL
multienc-0.1.0.dist-info/RECORD
